GPL2.0
INSTALL
LICENSE
MANIFEST.in
README.rst
ReleaseNotes.rst
setup.cfg
setup.py
scripts/tingyun-admin
tingyun/__init__.py
tingyun/api.py
tingyun/startup.py
tingyun/tingyun.ini
tingyun/version.py
tingyun.egg-info/PKG-INFO
tingyun.egg-info/SOURCES.txt
tingyun.egg-info/dependency_links.txt
tingyun.egg-info/entry_points.txt
tingyun.egg-info/top_level.txt
tingyun/__pycache__/__init__.cpython-36.pyc
tingyun/__pycache__/version.cpython-36.pyc
tingyun/armoury/__init__.py
tingyun/armoury/database_bmemcache.py
tingyun/armoury/database_dbapi2.py
tingyun/armoury/database_memcached.py
tingyun/armoury/database_mongo.py
tingyun/armoury/database_pymemcache.py
tingyun/armoury/database_redis.py
tingyun/armoury/external_httplib.py
tingyun/armoury/external_httplib2.py
tingyun/armoury/external_requests.py
tingyun/armoury/external_thrift.py
tingyun/armoury/external_urllib.py
tingyun/armoury/external_urllib2.py
tingyun/armoury/external_urllib3.py
tingyun/armoury/framework_bottle.py
tingyun/armoury/framework_django.py
tingyun/armoury/framework_flask.py
tingyun/armoury/framework_tornado.py
tingyun/armoury/framework_web2py.py
tingyun/armoury/framework_webpy.py
tingyun/armoury/template_jinja2.py
tingyun/armoury/template_mako.py
tingyun/armoury/ammunition/__init__.py
tingyun/armoury/ammunition/database_tracker.py
tingyun/armoury/ammunition/django_tracker.py
tingyun/armoury/ammunition/error_tracker.py
tingyun/armoury/ammunition/external_tracker.py
tingyun/armoury/ammunition/flask_tracker.py
tingyun/armoury/ammunition/function_tracker.py
tingyun/armoury/ammunition/memcache_tracker.py
tingyun/armoury/ammunition/mongo_tracker.py
tingyun/armoury/ammunition/mq_tracker.py
tingyun/armoury/ammunition/piston.py
tingyun/armoury/ammunition/redis_tracker.py
tingyun/armoury/ammunition/timer.py
tingyun/armoury/ammunition/tracker.py
tingyun/armoury/ammunition/web2py_trakcer.py
tingyun/armoury/ammunition/webpy_tracker.py
tingyun/armoury/ammunition/tornado/__init__.py
tingyun/armoury/ammunition/tornado/http_client.py
tingyun/armoury/ammunition/tornado/http_server.py
tingyun/armoury/ammunition/tornado/http_util.py
tingyun/armoury/ammunition/tornado/httpclient.py
