Metadata-Version: 1.1
Name: tingyun
Version: 1.3.6
Summary: Python application performance monitor client,It's main usage is working with python web application.
Home-page: http://www.tingyun.com
Author: tingyun.com
Author-email: python@tingyun.com 
License: (C) Copyright 2007-2017 networkbench Inc. All rights reserved.
Platform: unix
Platform: linux
Platform: MacOS
Classifier: Topic :: Internet :: WWW/HTTP
Classifier: Topic :: Software Development :: Libraries :: Python Modules
Classifier: License :: OSI Approved :: GNU General Public License (GPL)
Classifier: Development Status :: 4 - Beta
Classifier: Environment :: Web Environment
Classifier: Programming Language :: Python
Classifier: Programming Language :: Python :: 2
Classifier: Programming Language :: Python :: 2.6
Classifier: Programming Language :: Python :: 2.7
Classifier: Operating System :: MacOS :: MacOS X
Classifier: Operating System :: POSIX
Classifier: Operating System :: Unix
